{"nodes": [{"id": "authservice_authservice", "label": "AuthService (re-export)", "file_type": "code", "source_file": "frontend/src/Services/authService.js", "source_location": null, "source_url": null, "captured_at": null, "author": null, "contributor": null}], "edges": [{"source": "authservice_authservice", "target": "authapi_authapi", "relation": "references", "confidence": "EXTRACTED", "confidence_score": 1.0, "source_file": "frontend/src/Services/authService.js", "source_location": null, "weight": 1.0}, {"source": "authapi_authapi", "target": "authservice_authservice", "relation": "implements", "confidence": "EXTRACTED", "confidence_score": 1.0, "source_file": "frontend/src/Services/authService.js", "source_location": null, "weight": 1.0}], "hyperedges": []}